{
  "openapi": "3.0.1",
  "info": {
    "title": "AgendaMedica.API",
    "version": "1.0"
  },
  "paths": {
    "/api/Citas/agendar": {
      "post": {
        "tags": [
          "Citas"
        ],
        "requestBody": {
          "content": {
            "application/json": {
              "schema": {
                "$ref": "#/components/schemas/AgendarCitaRequest"
              }
            },
            "text/json": {
              "schema": {
                "$ref": "#/components/schemas/AgendarCitaRequest"
              }
            },
            "application/*+json": {
              "schema": {
                "$ref": "#/components/schemas/AgendarCitaRequest"
              }
            }
          }
        },
        "responses": {
          "200": {
            "description": "OK"
          }
        }
      }
    },
    "/api/Citas/cancelar": {
      "post": {
        "tags": [
          "Citas"
        ],
        "requestBody": {
          "content": {
            "application/json": {
              "schema": {
                "$ref": "#/components/schemas/CancelarCitaRequest"
              }
            },
            "text/json": {
              "schema": {
                "$ref": "#/components/schemas/CancelarCitaRequest"
              }
            },
            "application/*+json": {
              "schema": {
                "$ref": "#/components/schemas/CancelarCitaRequest"
              }
            }
          }
        },
        "responses": {
          "200": {
            "description": "OK"
          }
        }
      }
    },
    "/api/Citas/consultar/{id}": {
      "get": {
        "tags": [
          "Citas"
        ],
        "parameters": [
          {
            "name": "id",
            "in": "path",
            "required": true,
            "schema": {
              "type": "string"
            }
          }
        ],
        "requestBody": {
          "content": {
            "application/json": {
              "schema": {
                "$ref": "#/components/schemas/ConsultarCitaRequest"
              }
            },
            "text/json": {
              "schema": {
                "$ref": "#/components/schemas/ConsultarCitaRequest"
              }
            },
            "application/*+json": {
              "schema": {
                "$ref": "#/components/schemas/ConsultarCitaRequest"
              }
            }
          }
        },
        "responses": {
          "200": {
            "description": "OK"
          }
        }
      }
    },
    "/api/Medicos": {
      "get": {
        "tags": [
          "Medicos"
        ],
        "responses": {
          "200": {
            "description": "OK"
          }
        }
      },
      "post": {
        "tags": [
          "Medicos"
        ],
        "requestBody": {
          "content": {
            "application/json": {
              "schema": {
                "$ref": "#/components/schemas/AgregarMedicoRequest"
              }
            },
            "text/json": {
              "schema": {
                "$ref": "#/components/schemas/AgregarMedicoRequest"
              }
            },
            "application/*+json": {
              "schema": {
                "$ref": "#/components/schemas/AgregarMedicoRequest"
              }
            }
          }
        },
        "responses": {
          "200": {
            "description": "OK"
          }
        }
      }
    },
    "/api/Medicos/{id}": {
      "get": {
        "tags": [
          "Medicos"
        ],
        "parameters": [
          {
            "name": "id",
            "in": "path",
            "required": true,
            "schema": {
              "type": "string",
              "format": "uuid"
            }
          }
        ],
        "responses": {
          "200": {
            "description": "OK"
          }
        }
      },
      "put": {
        "tags": [
          "Medicos"
        ],
        "parameters": [
          {
            "name": "id",
            "in": "path",
            "required": true,
            "schema": {
              "type": "string"
            }
          }
        ],
        "requestBody": {
          "content": {
            "application/json": {
              "schema": {
                "$ref": "#/components/schemas/ActualizarMedicoRequest"
              }
            },
            "text/json": {
              "schema": {
                "$ref": "#/components/schemas/ActualizarMedicoRequest"
              }
            },
            "application/*+json": {
              "schema": {
                "$ref": "#/components/schemas/ActualizarMedicoRequest"
              }
            }
          }
        },
        "responses": {
          "200": {
            "description": "OK"
          }
        }
      },
      "delete": {
        "tags": [
          "Medicos"
        ],
        "parameters": [
          {
            "name": "id",
            "in": "path",
            "required": true,
            "schema": {
              "type": "string",
              "format": "uuid"
            }
          }
        ],
        "responses": {
          "200": {
            "description": "OK"
          }
        }
      }
    },
    "/api/Medicos/horarios/{id}/{fecha}": {
      "get": {
        "tags": [
          "Medicos"
        ],
        "parameters": [
          {
            "name": "id",
            "in": "path",
            "required": true,
            "schema": {
              "type": "string"
            }
          },
          {
            "name": "fecha",
            "in": "path",
            "required": true,
            "schema": {
              "type": "string"
            }
          }
        ],
        "requestBody": {
          "content": {
            "application/json": {
              "schema": {
                "$ref": "#/components/schemas/ProximosHorariosRequest"
              }
            },
            "text/json": {
              "schema": {
                "$ref": "#/components/schemas/ProximosHorariosRequest"
              }
            },
            "application/*+json": {
              "schema": {
                "$ref": "#/components/schemas/ProximosHorariosRequest"
              }
            }
          }
        },
        "responses": {
          "200": {
            "description": "OK"
          }
        }
      }
    },
    "/api/Medicos/agenda/{id}/{fecha}": {
      "get": {
        "tags": [
          "Medicos"
        ],
        "parameters": [
          {
            "name": "id",
            "in": "path",
            "required": true,
            "schema": {
              "type": "string",
              "format": "uuid"
            }
          },
          {
            "name": "fecha",
            "in": "path",
            "required": true,
            "schema": {
              "type": "string",
              "format": "date-time"
            }
          }
        ],
        "responses": {
          "200": {
            "description": "OK"
          }
        }
      }
    },
    "/api/Pacientes": {
      "get": {
        "tags": [
          "Pacientes"
        ],
        "responses": {
          "200": {
            "description": "OK"
          }
        }
      },
      "post": {
        "tags": [
          "Pacientes"
        ],
        "requestBody": {
          "content": {
            "application/json": {
              "schema": {
                "$ref": "#/components/schemas/AgregarPacienteRequest"
              }
            },
            "text/json": {
              "schema": {
                "$ref": "#/components/schemas/AgregarPacienteRequest"
              }
            },
            "application/*+json": {
              "schema": {
                "$ref": "#/components/schemas/AgregarPacienteRequest"
              }
            }
          }
        },
        "responses": {
          "200": {
            "description": "OK"
          }
        }
      }
    },
    "/api/Pacientes/{id}": {
      "get": {
        "tags": [
          "Pacientes"
        ],
        "parameters": [
          {
            "name": "id",
            "in": "path",
            "required": true,
            "schema": {
              "type": "string",
              "format": "uuid"
            }
          }
        ],
        "responses": {
          "200": {
            "description": "OK"
          }
        }
      },
      "put": {
        "tags": [
          "Pacientes"
        ],
        "parameters": [
          {
            "name": "id",
            "in": "path",
            "required": true,
            "schema": {
              "type": "string"
            }
          }
        ],
        "requestBody": {
          "content": {
            "application/json": {
              "schema": {
                "$ref": "#/components/schemas/ActualizarPacienteRequest"
              }
            },
            "text/json": {
              "schema": {
                "$ref": "#/components/schemas/ActualizarPacienteRequest"
              }
            },
            "application/*+json": {
              "schema": {
                "$ref": "#/components/schemas/ActualizarPacienteRequest"
              }
            }
          }
        },
        "responses": {
          "200": {
            "description": "OK"
          }
        }
      },
      "delete": {
        "tags": [
          "Pacientes"
        ],
        "parameters": [
          {
            "name": "id",
            "in": "path",
            "required": true,
            "schema": {
              "type": "string",
              "format": "uuid"
            }
          }
        ],
        "responses": {
          "200": {
            "description": "OK"
          }
        }
      }
    },
    "/api/Pacientes/historial/{id}": {
      "get": {
        "tags": [
          "Pacientes"
        ],
        "parameters": [
          {
            "name": "id",
            "in": "path",
            "required": true,
            "schema": {
              "type": "string",
              "format": "uuid"
            }
          }
        ],
        "responses": {
          "200": {
            "description": "OK"
          }
        }
      }
    }
  },
  "components": {
    "schemas": {
      "ActualizarMedicoRequest": {
        "type": "object",
        "properties": {
          "id": {
            "type": "string",
            "format": "uuid"
          },
          "nombre": {
            "type": "string",
            "nullable": true
          },
          "apellidoPaterno": {
            "type": "string",
            "nullable": true
          },
          "apellidoMaterno": {
            "type": "string",
            "nullable": true
          }
        },
        "additionalProperties": false
      },
      "ActualizarPacienteRequest": {
        "type": "object",
        "properties": {
          "id": {
            "type": "string",
            "format": "uuid"
          },
          "nombre": {
            "type": "string",
            "nullable": true
          },
          "apellidoPaterno": {
            "type": "string",
            "nullable": true
          },
          "apellidoMaterno": {
            "type": "string",
            "nullable": true
          },
          "fechaNacimiento": {
            "type": "string",
            "format": "date"
          },
          "numeroTelefono": {
            "type": "string",
            "nullable": true
          },
          "correoElectronico": {
            "type": "string",
            "nullable": true
          }
        },
        "additionalProperties": false
      },
      "AgendarCitaRequest": {
        "type": "object",
        "properties": {
          "medicoId": {
            "type": "string",
            "format": "uuid"
          },
          "pacienteId": {
            "type": "string",
            "format": "uuid"
          },
          "especialidadId": {
            "type": "string",
            "format": "uuid"
          },
          "fechaHora": {
            "type": "string",
            "format": "date-time"
          },
          "motivo": {
            "type": "string",
            "nullable": true
          }
        },
        "additionalProperties": false
      },
      "AgregarMedicoRequest": {
        "type": "object",
        "properties": {
          "nombre": {
            "type": "string",
            "nullable": true
          },
          "apellidoPaterno": {
            "type": "string",
            "nullable": true
          },
          "apellidoMaterno": {
            "type": "string",
            "nullable": true
          }
        },
        "additionalProperties": false
      },
      "AgregarPacienteRequest": {
        "type": "object",
        "properties": {
          "nombre": {
            "type": "string",
            "nullable": true
          },
          "apellidoPaterno": {
            "type": "string",
            "nullable": true
          },
          "apellidoMaterno": {
            "type": "string",
            "nullable": true
          },
          "fechaNacimiento": {
            "type": "string",
            "format": "date"
          },
          "numeroTelefono": {
            "type": "string",
            "nullable": true
          },
          "correoElectronico": {
            "type": "string",
            "nullable": true
          }
        },
        "additionalProperties": false
      },
      "CancelarCitaRequest": {
        "type": "object",
        "properties": {
          "id": {
            "type": "string",
            "format": "uuid"
          },
          "motivoCancelacion": {
            "type": "string",
            "nullable": true
          }
        },
        "additionalProperties": false
      },
      "ConsultarCitaRequest": {
        "type": "object",
        "properties": {
          "id": {
            "type": "string",
            "format": "uuid"
          }
        },
        "additionalProperties": false
      },
      "ProximosHorariosRequest": {
        "type": "object",
        "properties": {
          "id": {
            "type": "string",
            "format": "uuid"
          },
          "fecha": {
            "type": "string",
            "format": "date"
          }
        },
        "additionalProperties": false
      }
    }
  }
}